{
  "frutas_brasil": [
    {
      "nome": "Abiu",
      "origem": "Brasil",
      "estado_produtor": "MG, SP, PR, SC",
      "imagem": "https://i.postimg.cc/BbnZrmCv/abiu.png",
      "usada_em": "in natura, doces, geleias, licores",
      "nome_cientifico":" Pouteria caimito (Ruiz & Pav.) Radlk. Sinônimos incluem Lucuma caimito e Achras caimito."
    },
    {
      "nome": "Açaí",
      "origem": "Brasil",
      "estado_produtor": "PA, AM, MA",
      "imagem": "https://i.postimg.cc/WzsRCtT6/a-a.png",
      "usada_em": "sucos, vitaminas, cremes, tigelas",
      "nome_cientifico":"Euterpe oleracea."
    },
    {
      "nome": "Cupuaçu",
      "origem": "Brasil",
      "estado_produtor": "AM, PA, MA",
      "imagem": "https://i.postimg.cc/J7dVPrSJ/cupuacu.png",
      "usada_em": "sucos, doces, cremes, sorvetes",
      "nome_cientifico":"Theobroma grandiflorum."
    },
    {
      "nome": "Graviola",
      "origem": "América Tropical (possivelmente Brasil)",
      "estado_produtor": "BA, CE, PE",
      "imagem": "https://i.postimg.cc/L8PJm0jC/graviola.png",
      "usada_em": "sucos, sorvetes, doces",
      "nome_cientifico":"Annona muricata L."
    },
    {
      "nome": "Mangaba",
      "origem": "Brasil",
      "estado_produtor": "SE, AL, BA, MG",
      "imagem": "https://i.postimg.cc/L80F0HJG/mangaba.png",
      "usada_em": "in natura, sucos, doces, sorvetes",
      "nome_cientifico":"Hancornia speciosa Gomes."
    },
    {
      "nome": "Jaca",
      "origem": "Índia (naturalizada no Brasil)",
      "estado_produtor": "BA, RJ, SP",
      "imagem": "https://i.postimg.cc/yYmFPdbY/jaca.png",
      "usada_em": "in natura (fruto maduro e verde), pratos salgados (jaca verde)",
      "nome_cientifico":" Artocarpus heterophyllus Lam."
    },
    {
      "nome": "Pitanga",
      "origem": "Brasil",
      "estado_produtor": "SP, RJ, MG, RS",
      "imagem": "",
      "usada_em": "in natura, sucos, geleias, doces",
      "nome_cientifico":"Eugenia uniflora L."
    },
    {
      "nome": "Cajá",
      "origem": "América Tropical (possivelmente Brasil)",
      "estado_produtor": "PI, CE, PB",
      "imagem": "",
      "usada_em": "sucos, sorvetes, doces, geleias",
      "nome_cientifico":"Spondias mombin L."
    },
    {
      "nome": "Buriti",
      "origem": "Brasil",
      "estado_produtor": "MA, TO, MG",
      "imagem": "",
      "usada_em": "sucos, óleos, doces, in natura",
      "nome_cientifico":"Mauritia flexuosa L. f."
    },
    {
      "nome": "Maracujá",
      "origem": "Brasil",
      "estado_produtor": "SP, BA, SC",
      "imagem": "",
      "usada_em": "sucos, mousses, bolos, doces",
      "nome_cientifico":"Passiflora edulis Sims."
    },
    {
      "nome": "Jabuticaba",
      "origem": "Brasil",
      "estado_produtor": "MG, SP, RJ, PR",
      "imagem": "",
      "usada_em": "in natura, sucos, geleias, licores",
      "nome_cientifico":"Plinia cauliflora (Mart.) Kausel ou... Myrciaria cauliflora (Mart.) O. Berg"
    },
    {
      "nome": "Tamarindo",
      "origem": "África (naturalizada no Brasil)",
      "estado_produtor": "CE, BA, PI",
      "imagem": "",
      "usada_em": "sucos, doces, molhos",
      "nome_cientifico":"Tamarindus indica L."
    },
    {
      "nome": "Umbu",
      "origem": "Brasil",
      "estado_produtor": "BA, SE, PE",
      "imagem": "",
      "usada_em": "in natura, sucos, geleias, doces",
      "nome_cientifico":"Spondias tuberosa Arruda."
    },
    {
      "nome": "Acerola",
      "origem": "América Central e do Sul (possivelmente Brasil)",
      "estado_produtor": "CE, PE, BA",
      "imagem": "",
      "usada_em": "sucos, geleias, in natura",
      "nome_cientifico":"Malpighia emarginata DC."
    },
    {
      "nome": "Goiaba",
      "origem": "América Tropical (possivelmente Brasil)",
      "estado_produtor": "SP, PE, MG",
      "imagem": "https://upload.wikimedia.org/wikipedia/commons/thumb/c/c7/Goiabas.jpg/800px-Goiabas.jpg",
      "usada_em": "in natura, sucos, doces, geleias (goiabada)",
      "nome_cientifico":" Psidium guajava L."
    },
    {
      "nome": "Cacau",
      "origem": "Bacia Amazônica",
      "estado_produtor": "BA, PA, ES",
      "imagem": "https://upload.wikimedia.org/wikipedia/commons/thumb/6/64/Cacao_fruit_cut_open.jpg/800px-Cacao_fruit_cut_open.jpg",
      "usada_em": "chocolate, sucos, doces",
      "nome_cientifico":"Theobroma cacao L."
    }
  ]
}